elevenlabslib/Dub.py
elevenlabslib/HistoryItem.py
elevenlabslib/Model.py
elevenlabslib/Project.py
elevenlabslib/PronunciationDictionary.py
elevenlabslib/Sample.py
elevenlabslib/User.py
elevenlabslib/Voice.py
elevenlabslib/__init__.py
elevenlabslib/_audio_cutter_helper.py
elevenlabslib/helpers.py
elevenlabslib/utils.py
elevenlabslib-0.32.1.dist-info/licenses/LICENSE
elevenlabslib-0.32.1.dist-info/METADATA
elevenlabslib-0.32.1.dist-info/WHEEL
elevenlabslib-0.32.1.dist-info/top_level.txt
elevenlabslib-0.32.1.dist-info/RECORD
