Metadata-Version: 2.4
Name: elevenlabslib
Version: 0.32.1
Summary: Complete python wrapper for the elevenlabs API
Author-email: lugia19 <lugia19@lugia19.com>
Project-URL: Documentation, https://elevenlabslib.readthedocs.io/en/latest/
Project-URL: Homepage, https://github.com/lugia19/elevenlabslib
Project-URL: Bug Tracker, https://github.com/lugia19/elevenlabslib
Classifier: Programming Language :: Python :: 3
Classifier: License :: OSI Approved :: MIT License
Classifier: Operating System :: OS Independent
Classifier: Development Status :: 4 - Beta
Requires-Python: >=3.7
License-File: LICENSE
Requires-Dist: requests
Requires-Dist: sounddevice
Requires-Dist: numpy
Requires-Dist: soundfile>=0.12.1
Requires-Dist: websockets
Requires-Dist: fuzzywuzzy
Requires-Dist: python-Levenshtein
Requires-Dist: resampy
Requires-Dist: appdirs
Requires-Dist: onnxruntime
Requires-Dist: xmltodict
Requires-Dist: tokenizers
Dynamic: license-file
